neobulkmp/__init__.py
neobulkmp/cache_backend.py
neobulkmp/cache_logger.py
neobulkmp/worker_base.py
neobulkmp/worker_loading.py
neobulkmp/worker_sourcing.py
neobulkmp/manager/__init__.py
neobulkmp/manager/manager.py
neobulkmp/manager/manager_statistics.py
neobulkmp/manager/manager_strategies.py
neobulkmp/manager/manager_workers_base.py
neobulkmp/manager/manager_workers_loading.py
neobulkmp/manager/manager_workers_sourcing.py
neobulkmp-0.2.17.dist-info/METADATA
neobulkmp-0.2.17.dist-info/WHEEL
neobulkmp-0.2.17.dist-info/top_level.txt
neobulkmp-0.2.17.dist-info/RECORD
